{
    "id": 10000021,
    "ot": 3,
    "alias": 10000020,
    "setcode": 0,
    "type": 33,
    "atk": -2,
    "def": -2,
    "level": 10,
    "race": 2097152,
    "attribute": 64,
    "category": 8200,
    "name": "Slifer the Sky Dragon",
    "desc": "Requires 3 Tributes to Normal Summon (cannot be Normal Set). This card's Normal Summon cannot be negated. When Normal Summoned, cards and effects cannot be activated. Once per turn, during the End Phase, if this card was Special Summoned: Send it to the GY. Gains 1000 ATK and DEF for each card in your hand. If a monster(s) is Normal or Special Summoned to your opponent's field in Attack Position: That monster(s) loses 2000 ATK, then if its ATK has been reduced to 0 as a result, destroy it.",
    "str1": "Send to Graveyard",
    "str2": "Lower attack",
    "str3": "",
    "str4": "",
    "str5": "",
    "str6": "",
    "str7": "",
    "str8": "",
    "str9": "",
    "str10": "",
    "str11": "",
    "str12": "",
    "str13": "",
    "str14": "",
    "str15": "",
    "str16": "",
    "links": [],
    "cardpool": "OCG/TCG",
    "ocg": {
        "id": 10000021,
        "pack_id": "VJMP-JP064",
        "pack": "V Jump February 2012 promotional card",
        "rarity": "Slifer the Sky Dragon",
        "date": "2011-12-17"
    },
    "tcg": {
        "id": 10000021,
        "pack_id": "JUMP-EN061",
        "pack": "Weekly Shonen Jump Alpha July 2012 membership",
        "rarity": "Slifer the Sky Dragon",
        "date": "2012-08-27"
    },
    "picture": "https://vignette.wikia.nocookie.net/yugioh/images/8/8c/SlifertheSkyDragon-JMPS-EN-UR-LE.png"
}