{
    "ocg": {
        "pack": "LINK VRAINS Box",
        "pack_id": "LVB1-JP002",
        "date": "2017-12-23"
    },
    "tcg": {},
    "id": 100225002,
    "setcode": 0,
    "type": 33,
    "atk": 0,
    "def": 0,
    "level": 1,
    "race": 16777216,
    "attribute": 16,
    "name": "Formud Skipper",
    "desc": "During your Main Phase: You can reveal 1 Link Monster in your Extra Deck, and if you do, the name, Type, and Attribute of this face-up card on the field can be treated as the revealed monster's, if used as material for a Link Summon this turn. If this card is sent to the GY as material for a Link Summon: You can add 1 Level 5 or higher Cyberse monster from your Deck to your hand. You can only use each effect of \"Formud Skipper\" once per turn.",
    "picture": "https://vignette.wikia.nocookie.net/yugioh/images/c/c8/FormudSkkiper-LVB1-JP-OP.png"
}