{
    "id": 101012029,
    "ot": 1,
    "alias": 0,
    "setcode": 304,
    "type": 33,
    "atk": 1500,
    "def": 1500,
    "level": 3,
    "race": 8,
    "attribute": 32,
    "category": 17039360,
    "name": "Unchained Twins - Salama",
    "desc": "You can target 1 \"Unchained\" card in your GY, except \"Unchained Twins - Salama\"; Set it to your field, then destroy 1 card you control. If this card on the field is destroyed by card effect, except \"Unchained Twins - Salama\", or by battle: You can Special Summon 1 \"Unchained\" monster from your hand or Deck, except \"Unchained Twins - Salama\". You can only use each effect of \"Unchained Twins - Salama\" once per turn.",
    "str1": "",
    "str2": "",
    "str3": "",
    "str4": "",
    "str5": "",
    "str6": "",
    "str7": "",
    "str8": "",
    "str9": "",
    "str10": "",
    "str11": "",
    "str12": "",
    "str13": "",
    "str14": "",
    "str15": "",
    "str16": "",
    "cardpool": "OCG"
}