{
    "ocg": {
        "pack": "Flames of Destruction",
        "pack_id": "FLOD-JP054",
        "date": "2018-01-13"
    },
    "tcg": {},
    "id": 101004054,
    "setcode": 251,
    "type": 524290,
    "atk": 0,
    "def": 0,
    "level": 0,
    "race": 0,
    "attribute": 0,
    "name": "Trickstar Light Arena",
    "desc": "If you Link Summon a \"Trickstar\" monster: You can target 1 \"Trickstar\" monster in your GY, that was used as material for that Link Summon; Special Summon it in Defense Position, but it has its effects negated. You can only use this effect of \"Trickstar Light Arena\" once per turn. Once per turn: You can target 1 Set card in your opponent's Spell & Trap Zone; while this card is in the Field Zone, that Set card cannot be activated until the End Phase, and your opponent must activate it during the End Phase or else return it to the hand.",
    "picture": "https://vignette.wikia.nocookie.net/yugioh/images/6/63/TrickstarLightArena-FLOD-JP-OP.png"
}