{
    "id": 12057781,
    "ot": 3,
    "alias": 0,
    "setcode": 172,
    "type": 17,
    "atk": 400,
    "def": 400,
    "level": 1,
    "race": 8,
    "attribute": 32,
    "category": 0,
    "name": "Goblin Calligrapher",
    "desc": "A Goblin who devotes himself to mastering perfect calligraphy of the word \"False\". He gives his all to each stroke.",
    "str1": "",
    "str2": "",
    "str3": "",
    "str4": "",
    "str5": "",
    "str6": "",
    "str7": "",
    "str8": "",
    "str9": "",
    "str10": "",
    "str11": "",
    "str12": "",
    "str13": "",
    "str14": "",
    "str15": "",
    "str16": "",
    "links": [],
    "cardpool": "OCG/TCG",
    "ocg": {
        "id": 12057781,
        "pack_id": "SOD-JP004",
        "pack": "SOD",
        "rarity": "Goblin Calligrapher",
        "date": 1085616000000
    },
    "tcg": {
        "id": 12057781,
        "pack_id": "SOD-EN004",
        "pack": "SOD",
        "rarity": "Goblin Calligrapher",
        "date": 1096588800000
    }
}