{
    "id": 12863633,
    "ot": 3,
    "alias": 0,
    "setcode": 0,
    "type": 4,
    "atk": 0,
    "def": 0,
    "level": 0,
    "race": 0,
    "attribute": 0,
    "category": 0,
    "name": "Curse of the Circle",
    "desc": "Target 1 monster your opponent controls; your opponent cannot Tribute it, or use it as a Synchro Material Monster.",
    "str1": "",
    "str2": "",
    "str3": "",
    "str4": "",
    "str5": "",
    "str6": "",
    "str7": "",
    "str8": "",
    "str9": "",
    "str10": "",
    "str11": "",
    "str12": "",
    "str13": "",
    "str14": "",
    "str15": "",
    "str16": "",
    "links": [],
    "cardpool": "OCG/TCG",
    "ocg": {
        "pack": "Generation Force",
        "pack_id": "GENF-JP076",
        "date": "2011-04-16"
    },
    "tcg": {
        "pack": "Generation Force",
        "pack_id": "GENF-EN076",
        "date": "2011-08-06"
    },
    "picture": "https://vignette.wikia.nocookie.net/yugioh/images/2/24/CurseoftheCircle-GENF-EN-R-1E.jpg"
}