{
    "id": 14816688,
    "ot": 3,
    "alias": 0,
    "setcode": 0,
    "type": 2,
    "atk": 0,
    "def": 0,
    "level": 0,
    "race": 0,
    "attribute": 0,
    "category": 0,
    "name": "Shuffle Reborn",
    "desc": "If you control no monsters: Target 1 monster in your GY; Special Summon it, but it has its effects negated, also banish it during the End Phase. You can banish this card from your GY, then target 1 card you control; shuffle it into the Deck, then draw 1 card, also during the End Phase of this turn, banish 1 card from your hand. You can only use this effect of \"Shuffle Reborn\" once per turn.",
    "str1": "",
    "str2": "",
    "str3": "",
    "str4": "",
    "str5": "",
    "str6": "",
    "str7": "",
    "str8": "",
    "str9": "",
    "str10": "",
    "str11": "",
    "str12": "",
    "str13": "",
    "str14": "",
    "str15": "",
    "str16": "",
    "links": [],
    "cardpool": "OCG/TCG",
    "ocg": {
        "pack": "Dimension of Chaos",
        "pack_id": "DOCS-JP053",
        "date": "2015-07-18"
    },
    "tcg": {
        "pack": "Dimension of Chaos",
        "pack_id": "DOCS-DE053",
        "date": "2015-11-05"
    },
    "picture": "https://vignette.wikia.nocookie.net/yugioh/images/5/55/ShuffleReborn-SDCL-EN-C-1E.png"
}