{
    "id": 15452043,
    "ot": 3,
    "alias": 0,
    "setcode": 159,
    "type": 33,
    "atk": 600,
    "def": 600,
    "level": 2,
    "race": 131072,
    "attribute": 2,
    "category": 0,
    "name": "Performapal Sword Fish",
    "desc": "If this card is Normal or Special Summoned: All monsters your opponent currently controls lose 600 ATK and DEF. If you Special Summon a monster(s) while you control this card: All monsters your opponent currently controls lose 600 ATK and DEF.",
    "str1": "",
    "str2": "",
    "str3": "",
    "str4": "",
    "str5": "",
    "str6": "",
    "str7": "",
    "str8": "",
    "str9": "",
    "str10": "",
    "str11": "",
    "str12": "",
    "str13": "",
    "str14": "",
    "str15": "",
    "str16": "",
    "links": [],
    "cardpool": "OCG/TCG",
    "ocg": {
        "id": 15452043,
        "pack_id": "DUEA-JP007",
        "pack": "DUEA",
        "rarity": "Performapal Sword Fish",
        "date": "2014-04-19"
    },
    "tcg": {
        "id": 15452043,
        "pack_id": "DUEA-EN007",
        "pack": "DUEA",
        "rarity": "Performapal Sword Fish",
        "date": "2014-08-14"
    },
    "picture": "https://vignette.wikia.nocookie.net/yugioh/images/c/c0/PerformapalSwordFish-MP15-EN-C-1E.png/revision/latest?"
}