{
    "id": 17375316,
    "ot": 3,
    "alias": 0,
    "setcode": 0,
    "type": 2,
    "atk": 0,
    "def": 0,
    "level": 0,
    "race": 0,
    "attribute": 0,
    "category": 64,
    "name": "Confiscation",
    "desc": "Pay 1000 Life Points. Look at your opponent's hand, select 1 card in it and discard that card.",
    "str1": "",
    "str2": "",
    "str3": "",
    "str4": "",
    "str5": "",
    "str6": "",
    "str7": "",
    "str8": "",
    "str9": "",
    "str10": "",
    "str11": "",
    "str12": "",
    "str13": "",
    "str14": "",
    "str15": "",
    "str16": "",
    "links": [],
    "cardpool": "OCG/TCG",
    "ocg": {
        "id": 17375316,
        "pack_id": "MR-38",
        "pack": "MR",
        "rarity": "Confiscation",
        "date": "2000-04-20"
    },
    "tcg": {
        "id": 17375316,
        "pack_id": "MRL-038",
        "pack": "MRL",
        "rarity": "Confiscation",
        "date": "2002-09-16"
    },
    "picture": "https://vignette4.wikia.nocookie.net/yugioh/images/7/72/Confiscation-CP04-EN-R-UE.png/revision/latest?"
}