{
    "id": 19523799,
    "ot": 3,
    "alias": 0,
    "setcode": 0,
    "type": 2,
    "atk": 0,
    "def": 0,
    "level": 0,
    "race": 0,
    "attribute": 0,
    "category": 4194304,
    "name": "Ookazi",
    "desc": "Inflict 800 damage to your opponent.",
    "str1": "",
    "str2": "",
    "str3": "",
    "str4": "",
    "str5": "",
    "str6": "",
    "str7": "",
    "str8": "",
    "str9": "",
    "str10": "",
    "str11": "",
    "str12": "",
    "str13": "",
    "str14": "",
    "str15": "",
    "str16": "",
    "links": [],
    "cardpool": "OCG/TCG",
    "ocg": {
        "id": 19523799,
        "pack_id": "B1-31",
        "pack": "B1",
        "rarity": "Ookazi",
        "date": "1999-05-25"
    },
    "tcg": {
        "id": 19523799,
        "pack_id": "SDK-023",
        "pack": "SDK",
        "rarity": "Ookazi",
        "date": "2002-03-29"
    },
    "picture": "https://vignette.wikia.nocookie.net/yugioh/images/8/89/Ookazi-5DS2-EN-C-1E.png/revision/latest?"
}