{
    "id": 2359348,
    "ot": 3,
    "alias": 0,
    "setcode": 242,
    "type": 4,
    "atk": 0,
    "def": 0,
    "level": 0,
    "race": 0,
    "attribute": 0,
    "category": 0,
    "name": "Pendulum Area",
    "desc": "If all monsters you control are Pendulum Monsters (min. 1): Target 2 cards in your Pendulum Zones; destroy both cards, and if you do, neither player can Special Summon for the rest of this turn, except by Pendulum Summon.",
    "str1": "",
    "str2": "",
    "str3": "",
    "str4": "",
    "str5": "",
    "str6": "",
    "str7": "",
    "str8": "",
    "str9": "",
    "str10": "",
    "str11": "",
    "str12": "",
    "str13": "",
    "str14": "",
    "str15": "",
    "str16": "",
    "links": [],
    "cardpool": "OCG/TCG",
    "ocg": {
        "id": 2359348,
        "pack_id": "DOCS-JP077",
        "pack": "DOCS",
        "rarity": "Pendulum Area",
        "date": "2015-07-18"
    },
    "tcg": {
        "id": 2359348,
        "pack_id": "DOCS-EN077",
        "pack": "DOCS",
        "rarity": "Pendulum Area",
        "date": "2015-11-05"
    },
    "picture": "https://vignette.wikia.nocookie.net/yugioh/images/1/13/PendulumArea-DOCS-EN-R-1E.png/revision/latest?"
}