{
    "id": 23720856,
    "ot": 1,
    "alias": 0,
    "setcode": 5505167,
    "type": 33,
    "atk": 1800,
    "def": 100,
    "level": 4,
    "race": 1,
    "attribute": 1,
    "category": 0,
    "name": "Zubababanchou - Gagaga Coat",
    "desc": "If this card is in your hand and you control a \"Zubaba\" monster or \"Gagaga\" monster, except \"Zubababanchou - Gagaga Coat\": You can Special Summon this card. You can target 1 \"Gogogo\" monster or \"Dododo\" monster in your GY; Special Summon it, also you cannot Special Summon monsters from the Extra Deck for the rest of this turn, except Xyz Monsters. You can only use each effect of \"Zubababanchou - Gagaga Coat\" once per turn.",
    "str1": "Special Summon",
    "str2": "Special Summon",
    "str3": "Affected by \"Zubababanchou - Gagaga Coat\"",
    "str4": "",
    "str5": "",
    "str6": "",
    "str7": "",
    "str8": "",
    "str9": "",
    "str10": "",
    "str11": "",
    "str12": "",
    "str13": "",
    "str14": "",
    "str15": "",
    "str16": "",
    "cardpool": "OCG"
}