{
    "id": 28596933,
    "ot": 3,
    "alias": 0,
    "setcode": 0,
    "type": 2,
    "atk": 0,
    "def": 0,
    "level": 0,
    "race": 0,
    "attribute": 0,
    "category": 17,
    "name": "A Wingbeat of Giant Dragon",
    "desc": "Return 1 Level 5 or higher Dragon-Type monster you control to the hand, and if you do, destroy all Spell and Trap Cards on the field.",
    "str1": "",
    "str2": "",
    "str3": "",
    "str4": "",
    "str5": "",
    "str6": "",
    "str7": "",
    "str8": "",
    "str9": "",
    "str10": "",
    "str11": "",
    "str12": "",
    "str13": "",
    "str14": "",
    "str15": "",
    "str16": "",
    "links": [],
    "cardpool": "OCG/TCG",
    "ocg": {
        "pack": "Struggle of Chaos",
        "pack_id": "SC-44",
        "date": "2001-09-20"
    },
    "tcg": {
        "pack": "Legacy of Darkness",
        "pack_id": "LOD-044",
        "date": "2003-06-06"
    },
    "picture": "https://vignette.wikia.nocookie.net/yugioh/images/a/a4/AWingbeatofGiantDragon-SR02-EN-C-1E.png"
}