{
    "id": 32912040,
    "ot": 3,
    "alias": 0,
    "setcode": 226,
    "type": 33,
    "atk": 1800,
    "def": 700,
    "level": 4,
    "race": 256,
    "attribute": 1,
    "category": 0,
    "name": "Triamid Master",
    "desc": "Once per turn: You can send 1 face-up \"Triamid\" card you control to the Graveyard, then target 1 Set Card on the field; destroy it. Once per turn, during your opponent's turn: You can target 1 \"Triamid\" Field Spell Card in your Field Zone; send it to the Graveyard, and if you do, activate 1 \"Triamid\" Field Spell Card from your Deck with a different name (this is a Quick Effect).",
    "str1": "",
    "str2": "",
    "str3": "",
    "str4": "",
    "str5": "",
    "str6": "",
    "str7": "",
    "str8": "",
    "str9": "",
    "str10": "",
    "str11": "",
    "str12": "",
    "str13": "",
    "str14": "",
    "str15": "",
    "str16": "",
    "links": [],
    "cardpool": "OCG/TCG",
    "ocg": {
        "pack": "The Dark Illusion",
        "pack_id": "TDIL-JP029",
        "date": "2016-04-09"
    },
    "tcg": {
        "pack": "The Dark Illusion",
        "pack_id": "TDIL-DE029",
        "date": "2016-08-04"
    },
    "picture": "https://vignette.wikia.nocookie.net/yugioh/images/9/99/TriamidMaster-TDIL-EN-R-1E.png"
}