{
    "id": 36280194,
    "ot": 3,
    "alias": 0,
    "setcode": 0,
    "type": 4,
    "atk": 0,
    "def": 0,
    "level": 0,
    "race": 0,
    "attribute": 0,
    "category": 1024,
    "name": "Backup Soldier",
    "desc": "While there are 5 or more monsters in your Graveyard: Target up to 3 non-Effect Monsters with 1500 or less ATK in your Graveyard; add them to your hand.",
    "str1": "",
    "str2": "",
    "str3": "",
    "str4": "",
    "str5": "",
    "str6": "",
    "str7": "",
    "str8": "",
    "str9": "",
    "str10": "",
    "str11": "",
    "str12": "",
    "str13": "",
    "str14": "",
    "str15": "",
    "str16": "",
    "links": [],
    "cardpool": "OCG/TCG",
    "ocg": {
        "id": 36280194,
        "pack_id": "CA-28",
        "pack": "CA",
        "rarity": "Backup Soldier",
        "date": 970099200000
    },
    "tcg": {
        "id": 36280194,
        "pack_id": "PSV-028",
        "pack": "PSV",
        "rarity": "Backup Soldier",
        "date": 1035072000000
    }
}