{
    "id": 38606913,
    "ot": 1,
    "alias": 0,
    "setcode": 227,
    "type": 4,
    "atk": 0,
    "def": 0,
    "level": 0,
    "race": 0,
    "attribute": 0,
    "category": 71303168,
    "name": "Cubic Omen",
    "desc": "Place Cubic Counters on a face-up monster(s) your opponent controls, up to the number of \"Cubic\" monsters you control. (Monsters with a Cubic Counter cannot attack, also negate their effects.) You can banish this card from your GY, then target 1 \"Cubic\" monster you control; this turn, each time it destroys a monster with a Cubic Counter by battle, inflict damage to your opponent equal to the destroyed monster's original ATK. You can only use each effect of \"Cubic Omen\" once per turn.",
    "str1": "Place Counters",
    "str2": "Inflict Damage",
    "str3": "Inflict Damage",
    "str4": "Affected by \"Cubic Omen\"",
    "str5": "",
    "str6": "",
    "str7": "",
    "str8": "",
    "str9": "",
    "str10": "",
    "str11": "",
    "str12": "",
    "str13": "",
    "str14": "",
    "str15": "",
    "str16": "",
    "cardpool": "OCG"
}