{
    "id": 41440817,
    "ot": 3,
    "alias": 0,
    "setcode": 0,
    "type": 4,
    "atk": 0,
    "def": 0,
    "level": 0,
    "race": 0,
    "attribute": 0,
    "category": 32,
    "name": "Jelly Cannon",
    "desc": "When a monster declares an attack: Target 1 monster on the field; shuffle it into the Deck.",
    "str1": "",
    "str2": "",
    "str3": "",
    "str4": "",
    "str5": "",
    "str6": "",
    "str7": "",
    "str8": "",
    "str9": "",
    "str10": "",
    "str11": "",
    "str12": "CHIM-JP",
    "str13": "",
    "str14": "",
    "str15": "",
    "str16": "",
    "cardpool": "OCG/TCG"
}