{
    "id": 42632209,
    "ot": 3,
    "alias": 0,
    "setcode": 306,
    "type": 8225,
    "atk": 3000,
    "def": 0,
    "level": 12,
    "race": 16777216,
    "attribute": 4,
    "category": 512,
    "name": "Geomathmech Final Sigma",
    "desc": "1 Tuner + 1+ non-Tuner monsters\r\nUnaffected by card effects, except \"Mathmech\" cards, while in the Extra Monster Zone. If this card in the Extra Monster Zone battles an opponent's monster, any battle damage it inflicts to your opponent is doubled. If this card is destroyed by battle, or if this card in its owner's possession is destroyed by an opponent's card effect: You can add 1 \"Mathmech\" card from your Deck to your hand. You can only use this effect of \"Geomathmech Final Sigma\" once per turn.",
    "str1": "",
    "str2": "Search deck",
    "str3": "",
    "str4": "",
    "str5": "",
    "str6": "",
    "str7": "",
    "str8": "",
    "str9": "",
    "str10": "",
    "str11": "",
    "str12": "",
    "str13": "",
    "str14": "",
    "str15": "",
    "str16": "",
    "cardpool": "OCG/TCG"
}