{
    "id": 44877690,
    "ot": 3,
    "alias": 0,
    "setcode": 47,
    "type": 545,
    "atk": 1600,
    "def": 1200,
    "level": 4,
    "race": 16,
    "attribute": 2,
    "category": 16,
    "name": "Sacred Spirit of the Ice Barrier",
    "desc": "This card cannot be Special Summoned. This card returns to the hand during the End Phase of the turn it is Normal Summoned or flipped face-up, unless you control another face-up \"Ice Barrier\" monster. In that case, this card's effect changes to select 1 monster your opponent controls and return it to the hand, instead.",
    "str1": "Return to hand",
    "str2": "",
    "str3": "",
    "str4": "",
    "str5": "",
    "str6": "",
    "str7": "",
    "str8": "",
    "str9": "",
    "str10": "",
    "str11": "",
    "str12": "",
    "str13": "",
    "str14": "",
    "str15": "",
    "str16": "",
    "links": [],
    "cardpool": "OCG/TCG",
    "ocg": {
        "id": 44877690,
        "pack_id": "DT07-JP034",
        "pack": "DT07",
        "rarity": "Sacred Spirit of the Ice Barrier",
        "date": "2012-11-06"
    },
    "tcg": {
        "id": 44877690,
        "pack_id": "DT04-EN034",
        "pack": "DT04",
        "rarity": "Sacred Spirit of the Ice Barrier",
        "date": "2011-01-25"
    },
    "picture": "https://vignette3.wikia.nocookie.net/yugioh/images/a/a2/SacredSpiritoftheIceBarrier-HA04-EN-SR-1E.jpg/revision/latest?"
}