{
    "id": 47027714,
    "ot": 3,
    "alias": 0,
    "setcode": 273612839,
    "type": 33554465,
    "atk": 4500,
    "def": 4500,
    "level": 12,
    "race": 32,
    "attribute": 1,
    "category": 2147745792,
    "name": "T.G. Halberd Cannon/Assault Mode",
    "desc": "Cannot be Normal Summoned/Set. Must be Special Summoned with \"Assault Mode Activate\". You can only use each of the following effects of \"T.G. Halberd Cannon/Assault Mode\" once per turn.\r\n● When your opponent would Summon a monster (Quick Effect): You can negate the Summon, and if you do, banish that monster and all Special Summoned monsters your opponent controls.\r\n● When this card on the field is destroyed: You can target 1 \"T.G. Halberd Cannon\" in your GY; Special Summon it, ignoring its Summoning conditions.",
    "str1": "Negate Summon",
    "str2": "",
    "str3": "",
    "str4": "",
    "str5": "",
    "str6": "",
    "str7": "",
    "str8": "",
    "str9": "",
    "str10": "",
    "str11": "",
    "str12": "",
    "str13": "",
    "str14": "",
    "str15": "",
    "str16": "",
    "cardpool": "OCG/TCG"
}