{
    "ocg": {
        "pack": "LINK VRAINS Edition",
        "pack_id": "VP17-JP003",
        "date": "2017-07-21"
    },
    "tcg": {
        "pack": "Weekly Shonen Jump January 2018 membership",
        "pack_id": "JUMP-EN083",
        "date": "2018-02-01"
    },
    "id": 51011872,
    "setcode": 251,
    "type": 33554465,
    "atk": 2000,
    "def": "-",
    "level": 2,
    "race": 4,
    "attribute": 16,
    "name": "Trickstar Crimson Heart",
    "desc": "Link Arrows: [🡷][🡲]\n\n2 \"Trickstar\" monsters\nEach time a \"Trickstar\" monster(s) is Normal or Special Summoned to a zone(s) this card points to, gain 200 LP. You can discard 1 \"Trickstar\" card; both players draw 1 card, but if your LP was at least 2000 higher than your opponent's when this effect was activated, you draw 2 cards instead. You can only use this effect of \"Trickstar Crimson Heart\" once per turn.",
    "links": [
        4,
        5
    ],
    "picture": "https://vignette.wikia.nocookie.net/yugioh/images/5/54/TrickstarCrimsonHeart-SAST-EN-SR-LE.png"
}