{
    "id": 56292140,
    "ot": 3,
    "alias": 0,
    "setcode": 4718729,
    "type": 8388641,
    "atk": 2600,
    "def": 0,
    "level": 3,
    "race": 256,
    "attribute": 1,
    "category": 0,
    "name": "Number 51: Finisher the Strong Arm",
    "desc": "3 Level 3 monsters\nCannot be destroyed by battle. At the end of the Damage Step, if this card battled: You can detach 1 Xyz Material from this card; place 1 Counter on this card (max. 3). At the end of the Battle Phase, if this card battled, and has 3 of these Counters: You can destroy all cards your opponent controls.",
    "str1": "Add 1 Counter",
    "str2": "Destroy opponent cards",
    "str3": "",
    "str4": "",
    "str5": "",
    "str6": "",
    "str7": "",
    "str8": "",
    "str9": "",
    "str10": "",
    "str11": "",
    "str12": "",
    "str13": "",
    "str14": "",
    "str15": "",
    "str16": "",
    "links": [],
    "cardpool": "OCG/TCG",
    "ocg": {
        "id": 56292140,
        "pack_id": "CPF1-JP024",
        "pack": "Collectors Pack: Duelist of Flash Version",
        "rarity": "Number 51: Finisher the Strong Arm",
        "date": "2016-05-14"
    },
    "tcg": {
        "id": 56292140,
        "pack_id": "DRL3-DE024",
        "pack": "Dragons of Legend: Unleashed",
        "rarity": "Number 51: Finisher the Strong Arm",
        "date": "2016-08-18"
    },
    "picture": "https://vignette.wikia.nocookie.net/yugioh/images/2/23/Number51FinishertheStrongArm-DRL3-EN-ScR-1E.png"
}