{
    "id": 60577362,
    "ot": 3,
    "alias": 0,
    "setcode": 0,
    "type": 2,
    "atk": 0,
    "def": 0,
    "level": 0,
    "race": 0,
    "attribute": 0,
    "category": 131072,
    "name": "Overpowering Eye",
    "desc": "Target 1 Zombie monster you control with 2000 or less ATK; it can attack directly this turn.",
    "str1": "",
    "str2": "",
    "str3": "",
    "str4": "",
    "str5": "",
    "str6": "",
    "str7": "",
    "str8": "",
    "str9": "",
    "str10": "",
    "str11": "",
    "str12": "",
    "str13": "",
    "str14": "",
    "str15": "",
    "str16": "",
    "links": [],
    "cardpool": "OCG/TCG",
    "ocg": {
        "pack": "Premium Pack 8",
        "pack_id": "PP8-JP005",
        "date": "2004-12-18"
    },
    "tcg": {
        "pack": "Storm of Ragnarok",
        "pack_id": "STOR-EN094",
        "date": "2011-02-08"
    },
    "picture": "https://vignette.wikia.nocookie.net/yugioh/images/3/3b/OverpoweringEye-SR07-EN-C-1E.png"
}