{
    "id": 6077601,
    "ot": 3,
    "alias": 0,
    "setcode": 11337798,
    "type": 2,
    "atk": 0,
    "def": 0,
    "level": 0,
    "race": 0,
    "attribute": 0,
    "category": 0,
    "name": "Frightfur Fusion",
    "desc": "Fusion Summon 1 \"Frightfur\" Fusion Monster from your Extra Deck, by banishing Fusion Materials listed on it from your field or Graveyard. You can only activate 1 \"Frightfur Fusion\" per turn.",
    "str1": "",
    "str2": "",
    "str3": "",
    "str4": "",
    "str5": "",
    "str6": "",
    "str7": "",
    "str8": "",
    "str9": "",
    "str10": "",
    "str11": "",
    "str12": "",
    "str13": "",
    "str14": "",
    "str15": "",
    "str16": "",
    "links": [],
    "cardpool": "OCG/TCG",
    "ocg": {
        "pack": "Crossed Souls",
        "pack_id": "CROS-JP056",
        "date": "2015-02-14"
    },
    "tcg": {
        "pack": "Crossed Souls",
        "pack_id": "CROS-DE056",
        "date": "2015-05-14"
    },
    "picture": "https://vignette.wikia.nocookie.net/yugioh/images/9/9a/FrightfurFusion-SP17-EN-C-1E.png"
}