{
    "id": 63503850,
    "ot": 1,
    "alias": 0,
    "setcode": 0,
    "type": 67108897,
    "atk": 1600,
    "def": 5,
    "level": 2,
    "race": 16777216,
    "attribute": 32,
    "category": 16777216,
    "name": "Brute Enforcer",
    "desc": "Link Arrows: [🡷][🡶]\n\n2 Effect Monsters\nYou can discard 1 card, then target 1 face-up card your opponent controls; your opponent can discard 1 card with the same original card type (Monster, Spell, or Trap) as that face-up card to negate this effect, otherwise destroy that face-up card. You can only use this effect of \"Brute Enforcer\" once per turn.",
    "str1": "Destroy",
    "str2": "Discard 1 card to negate the effect of \"Brute Enforcer\"?",
    "str3": "",
    "str4": "",
    "str5": "",
    "str6": "",
    "str7": "",
    "str8": "",
    "str9": "",
    "str10": "",
    "str11": "",
    "str12": "",
    "str13": "",
    "str14": "",
    "str15": "",
    "str16": "",
    "cardpool": "OCG",
    "tcg": {},
    "ocg": {
        "pack": "LINK VRAINS Duelist Set",
        "pack_id": "LVDS-JPA02",
        "date": "2019-08-31"
    },
    "links": [
        5,
        7
    ],
    "picture": "https://vignette.wikia.nocookie.net/yugioh/images/9/90/BruteEnforcer-LVDS-JP-OP.png"
}