{
    "id": 65848811,
    "ot": 3,
    "alias": 0,
    "setcode": 7278703,
    "type": 33,
    "atk": 1800,
    "def": 200,
    "level": 4,
    "race": 1,
    "attribute": 1,
    "category": 0,
    "name": "Heroic Challenger - Assault Halberd",
    "desc": "If your opponent controls a monster and you control no monsters, you can Special Summon this card (from your hand). If this card attacks a Defense Position monster, inflict piercing battle damage to your opponent. When this card inflicts battle damage to your opponent: You can add 1 \"Heroic\" card from your Deck to your hand.",
    "str1": "Add 1 \"Heroic\" card from your Deck to your hand?",
    "str2": "",
    "str3": "",
    "str4": "",
    "str5": "",
    "str6": "",
    "str7": "",
    "str8": "",
    "str9": "",
    "str10": "",
    "str11": "",
    "str12": "",
    "str13": "",
    "str14": "",
    "str15": "",
    "str16": "",
    "links": [],
    "cardpool": "OCG/TCG",
    "ocg": {
        "id": 65848811,
        "pack_id": "DUEA-JP081",
        "pack": "Duelist Alliance",
        "rarity": "Heroic Challenger - Assault Halberd",
        "date": "2014-04-19"
    },
    "tcg": {
        "id": 65848811,
        "pack_id": "WSUP-DE016",
        "pack": "World Superstars",
        "rarity": "Heroic Challenger - Assault Halberd",
        "date": "2015-04-16"
    },
    "picture": "https://vignette.wikia.nocookie.net/yugioh/images/3/3b/HeroicChallengerAssaultHalberd-WSUP-EN-SR-1E.png/revision/latest?cb=20150412012556"
}