{
    "id": 68018709,
    "ot": 3,
    "alias": 0,
    "setcode": 0,
    "type": 33,
    "atk": 100,
    "def": 2000,
    "level": 4,
    "race": 4,
    "attribute": 16,
    "category": 0,
    "name": "Condemned Maiden",
    "desc": "During your opponent's turn, you can activate 1 Quick-Play Spell Card from your hand. You can only use this effect of \"Condemned Maiden\" once per Duel.",
    "str1": "Activate effect?",
    "str2": "",
    "str3": "",
    "str4": "",
    "str5": "",
    "str6": "",
    "str7": "",
    "str8": "",
    "str9": "",
    "str10": "",
    "str11": "",
    "str12": "",
    "str13": "",
    "str14": "",
    "str15": "",
    "str16": "",
    "links": [],
    "cardpool": "OCG/TCG",
    "ocg": {
        "id": 68018709,
        "pack_id": "PRIO-JP038",
        "pack": "PRIO",
        "rarity": "Condemned Maiden",
        "date": "2014-02-15"
    },
    "tcg": {
        "id": 68018709,
        "pack_id": "PRIO-EN038",
        "pack": "PRIO",
        "rarity": "Condemned Maiden",
        "date": "2014-05-16"
    },
    "picture": "https://vignette1.wikia.nocookie.net/yugioh/images/4/4d/CondemnedMaiden-PRIO-EN-SP-1E.png/revision/latest?"
}