{
    "id": 69211541,
    "ot": 3,
    "alias": 0,
    "setcode": 159,
    "type": 16777249,
    "atk": 500,
    "def": 2100,
    "level": 50528261,
    "race": 524288,
    "attribute": 1,
    "category": 0,
    "name": "Performapal Partnaga",
    "desc": "Pendulum Effect\nOnce per turn: You can target 1 face-up monster you control; it gains 300 ATK for each \"Performapal\" card you currently control, until the end of this turn.\n\nMonster Effect\nIf this card is Normal or Special Summoned: You can target 1 monster you control; it gains 300 ATK for each \"Performapal\" monster you currently control. Level 5 or lower monsters cannot attack.",
    "str1": "",
    "str2": "",
    "str3": "",
    "str4": "",
    "str5": "",
    "str6": "",
    "str7": "",
    "str8": "",
    "str9": "",
    "str10": "",
    "str11": "",
    "str12": "",
    "str13": "",
    "str14": "",
    "str15": "",
    "str16": "",
    "links": [],
    "cardpool": "OCG/TCG",
    "ocg": {
        "id": 69211541,
        "pack_id": "SECE-JP002",
        "pack": "Secrets of Eternity",
        "rarity": "Performapal Partnaga",
        "date": "2014-11-15"
    },
    "tcg": {
        "id": 69211541,
        "pack_id": "SECE-DE002",
        "pack": "Secrets of Eternity",
        "rarity": "Performapal Partnaga",
        "date": "2015-01-15"
    },
    "picture": "https://vignette.wikia.nocookie.net/yugioh/images/3/3e/PerformapalPartnaga-MP15-EN-C-1E.png"
}