{"id":69982329,"ot":3,"alias":0,"setcode":0,"type":65538,"atk":0,"def":0,"level":0,"race":0,"attribute":0,"category":0,"name":"Pendulum Shift","desc":"Target 1 card in either player's Pendulum Zone and declare a Pendulum Scale from 1 to 10; this turn, that card becomes that Pendulum Scale.","str1":"","str2":"","str3":"","str4":"","str5":"","str6":"","str7":"","str8":"","str9":"","str10":"","str11":"","str12":"","str13":"","str14":"","str15":"","str16":"","links":[],"cardpool":"OCG/TCG","ocg":{"id":69982329,"pack_id":"SECE-JP065","pack":"SECE","rarity":"Pendulum Shift","date":1416009600000},"tcg":{"id":69982329,"pack_id":"SECE-EN065","pack":"SECE","rarity":"Pendulum Shift","date":1421280000000}}