{
    "id": 73134081,
    "ot": 3,
    "alias": 0,
    "setcode": 0,
    "type": 2,
    "atk": 0,
    "def": 0,
    "level": 0,
    "race": 0,
    "attribute": 0,
    "category": 4194304,
    "name": "Final Flame",
    "desc": "Inflict 600 points of damage to your opponent's Life Points.",
    "str1": "",
    "str2": "",
    "str3": "",
    "str4": "",
    "str5": "",
    "str6": "",
    "str7": "",
    "str8": "",
    "str9": "",
    "str10": "",
    "str11": "",
    "str12": "",
    "str13": "",
    "str14": "",
    "str15": "",
    "str16": "",
    "links": [],
    "cardpool": "OCG/TCG",
    "ocg": {
        "id": 73134081,
        "pack_id": "PG-39",
        "pack": "PG",
        "rarity": "Final Flame",
        "date": 922492800000
    },
    "tcg": {
        "id": 73134081,
        "pack_id": "LOB-100",
        "pack": "LOB",
        "rarity": "Final Flame",
        "date": 1015545600000
    }
}