{
    "id": 7634581,
    "ot": 3,
    "alias": 0,
    "setcode": 0,
    "type": 33,
    "atk": -2,
    "def": 0,
    "level": 10,
    "race": 32,
    "attribute": 32,
    "category": 17047552,
    "name": "Orichalcos Shunoros",
    "desc": "This card cannot be Normal Summoned or Set. If a Normal Monster you control is destroyed by battle, you can Special Summon this card from your hand. This card gains 1000 ATK for each monster your opponent controls. Face-up Level 4 Normal Monsters on the field cannot be destroyed by card effects.",
    "str1": "",
    "str2": "",
    "str3": "",
    "str4": "",
    "str5": "",
    "str6": "",
    "str7": "",
    "str8": "",
    "str9": "",
    "str10": "",
    "str11": "",
    "str12": "",
    "str13": "",
    "str14": "",
    "str15": "",
    "str16": "",
    "links": [],
    "cardpool": "OCG/TCG",
    "ocg": {
        "id": 7634581,
        "pack_id": "LE15-JP001",
        "pack": "Limited Edition 15",
        "rarity": "Orichalcos Shunoros",
        "date": "2009-05-21"
    },
    "tcg": {
        "id": 7634581,
        "pack_id": "GLD4-FR029",
        "pack": "Gold Series 4: Pyramids Edition",
        "rarity": "Orichalcos Shunoros",
        "date": "2011-06-21"
    },
    "picture": "https://vignette.wikia.nocookie.net/yugioh/images/3/3c/OrichalcosShunoros-GLD4-EN-C-LE.png/revision/latest?cb=20110702010122"
}