{
    "id": 86170989,
    "ot": 3,
    "alias": 0,
    "setcode": 0,
    "type": 33,
    "atk": 1200,
    "def": 800,
    "level": 4,
    "race": 32,
    "attribute": 16,
    "category": 3407880,
    "name": "Falchionβ",
    "desc": "If this card destroys an opponent's monster by battle: Activate 1 of these effects.\n● Send 1 LIGHT Machine-Type monster with 1200 or less ATK from your Deck to your Graveyard.\n● Target 1 LIGHT Machine-Type monster with 1200 or less ATK in your Graveyard; Special Summon that target.",
    "str1": "Select effect",
    "str2": "Send 1 LIGHT Machine-Type monster with 1200 or less ATK from your Deck to your Graveyard.",
    "str3": "Special Summon 1 LIGHT Machine-Type monster with 1200 or less ATK from your Graveyard.",
    "str4": "",
    "str5": "",
    "str6": "",
    "str7": "",
    "str8": "",
    "str9": "",
    "str10": "",
    "str11": "",
    "str12": "",
    "str13": "",
    "str14": "",
    "str15": "",
    "str16": "",
    "links": [],
    "cardpool": "OCG/TCG",
    "ocg": {
        "pack": "Ancient Prophecy",
        "pack_id": "ANPR-JP039",
        "date": "2009-04-18"
    },
    "tcg": {
        "pack": "Ancient Prophecy",
        "pack_id": "ANPR-DE039",
        "date": "2009-08-27"
    },
    "picture": "https://vignette.wikia.nocookie.net/yugioh/images/9/9d/Falchion%CE%B2-SDCR-EN-C-1E.png"
}