{
    "id": 88289295,
    "ot": 3,
    "alias": 0,
    "setcode": 0,
    "type": 65538,
    "atk": 0,
    "def": 0,
    "level": 0,
    "race": 0,
    "attribute": 0,
    "category": 4096,
    "name": "Synchro Control",
    "desc": "Activate only if you have no Synchro Monsters on your side of the field or in your Graveyard. Pay 1000 Life Points and select 1 face-up Synchro Monster your opponent controls. Take control of the selected monster until the End Phase of your turn.",
    "str1": "",
    "str2": "",
    "str3": "",
    "str4": "",
    "str5": "",
    "str6": "",
    "str7": "",
    "str8": "",
    "str9": "",
    "str10": "",
    "str11": "",
    "str12": "",
    "str13": "",
    "str14": "",
    "str15": "",
    "str16": "",
    "links": [],
    "cardpool": "OCG/TCG",
    "ocg": {
        "id": 88289295,
        "pack_id": "ABPF-JP062",
        "pack": "ABPF",
        "rarity": "Synchro Control",
        "date": "2009-11-14"
    },
    "tcg": {
        "id": 88289295,
        "pack_id": "ABPF-EN062",
        "pack": "ABPF",
        "rarity": "Synchro Control",
        "date": "2010-02-12"
    },
    "picture": "https://vignette4.wikia.nocookie.net/yugioh/images/e/ea/SynchroControl-ABPF-EN-SR-1E.png/revision/latest?"
}