{
    "id": 91020571,
    "ot": 3,
    "alias": 0,
    "setcode": 0,
    "type": 33,
    "atk": 1800,
    "def": 1200,
    "level": 4,
    "race": 8192,
    "attribute": 1,
    "category": 262656,
    "name": "Reactan, Dragon Ruler of Pebbles",
    "desc": "You can discard this card AND 1 Dragon-Type or EARTH monster; Special Summon 1 \"Redox, Dragon Ruler of Boulders\" from your Deck. It cannot attack this turn. You can only use the effect of \"Reactan, Dragon Ruler of Pebbles\" once per turn.",
    "str1": "Special Summon",
    "str2": "",
    "str3": "",
    "str4": "",
    "str5": "",
    "str6": "",
    "str7": "",
    "str8": "",
    "str9": "",
    "str10": "",
    "str11": "",
    "str12": "",
    "str13": "",
    "str14": "",
    "str15": "",
    "str16": "",
    "links": [],
    "cardpool": "OCG/TCG",
    "ocg": {
        "id": 91020571,
        "pack_id": "PR03-JP001",
        "pack": "Promotion Pack 3: Part A",
        "rarity": "Reactan, Dragon Ruler of Pebbles",
        "date": "2013-02-15"
    },
    "tcg": {
        "id": 91020571,
        "pack_id": "LTGY-DE095",
        "pack": "Lord of the Tachyon Galaxy",
        "rarity": "Reactan, Dragon Ruler of Pebbles",
        "date": "2013-05-16"
    },
    "picture": "https://vignette.wikia.nocookie.net/yugioh/images/3/34/ReactanDragonRulerofPebbles-LTGY-EN-C-1E.png"
}