{
    "id": 94042337,
    "ot": 3,
    "alias": 0,
    "setcode": 0,
    "type": 17,
    "atk": 1550,
    "def": 800,
    "level": 4,
    "race": 64,
    "attribute": 2,
    "category": 0,
    "name": "Violent Rain",
    "desc": "This monster can call forth sudden torrents of battering rain.",
    "str1": "",
    "str2": "",
    "str3": "",
    "str4": "",
    "str5": "",
    "str6": "",
    "str7": "",
    "str8": "",
    "str9": "",
    "str10": "",
    "str11": "",
    "str12": "",
    "str13": "",
    "str14": "",
    "str15": "",
    "str16": "",
    "links": [],
    "cardpool": "OCG/TCG",
    "ocg": {
        "id": 94042337,
        "pack_id": "Great Moth",
        "pack": "Great Moth",
        "rarity": "共通",
        "date": "1999-11-18"
    },
    "tcg": {
        "id": 94042337,
        "pack_id": "TP8-EN015",
        "pack": "TP8",
        "rarity": "Violent Rain",
        "date": "2006-04-28"
    },
    "picture": "https://vignette3.wikia.nocookie.net/yugioh/images/1/10/ViolentRain-TP8-EN-C-UE.jpg/revision/latest?"
}