{
    "id": 9581215,
    "ot": 3,
    "alias": 0,
    "setcode": 137,
    "type": 4,
    "atk": 0,
    "def": 0,
    "level": 0,
    "race": 0,
    "attribute": 0,
    "category": 4,
    "name": "Chain Hole",
    "desc": "When your opponent activates a monster effect in response to a card or effect activation: Negate that opponent's effect, then, your opponent can banish 1 card from their hand or Deck with the same original name as that negated card. If they did not, you can banish 1 random card from their hand.",
    "str1": "Banish a card with the same name as the negated card?",
    "str2": "Banish a random card from the opponent's hand?",
    "str3": "",
    "str4": "",
    "str5": "",
    "str6": "",
    "str7": "",
    "str8": "",
    "str9": "",
    "str10": "",
    "str11": "",
    "str12": "",
    "str13": "",
    "str14": "",
    "str15": "",
    "str16": "",
    "cardpool": "OCG/TCG"
}