{
    "id": 96220350,
    "ot": 3,
    "alias": 0,
    "setcode": 0,
    "type": 97,
    "atk": 3000,
    "def": 2200,
    "level": 10,
    "race": 1,
    "attribute": 16,
    "category": 8720,
    "name": "Idaten the Conqueror Star",
    "desc": "2 Level 5 or higher Warrior monsters\r\nIf this card is Fusion Summoned: You can add 1 Level 5 Warrior monster from your Deck to your hand. You can only use this effect of \"Idaten the Conqueror Star\" once per turn. Once per turn: You can discard any number of cards; this card gains 200 ATK for each card discarded. Once per battle, during damage calculation, if this card battles an opponent's monster with an equal or lower Level (Quick Effect): You can make that opponent's monster's ATK 0 during that damage calculation only.",
    "str1": "Increase ATK",
    "str2": "Search deck",
    "str3": "",
    "str4": "",
    "str5": "",
    "str6": "",
    "str7": "",
    "str8": "",
    "str9": "",
    "str10": "",
    "str11": "",
    "str12": "",
    "str13": "",
    "str14": "",
    "str15": "",
    "str16": "",
    "cardpool": "OCG/TCG"
}