{
    "id": 97151365,
    "ot": 3,
    "alias": 0,
    "setcode": 0,
    "type": 131076,
    "atk": 0,
    "def": 0,
    "level": 0,
    "race": 0,
    "attribute": 0,
    "category": 262144,
    "name": "Spacegate",
    "desc": "Each time a monster your opponent controls attacks or is attacked, place 1 Gate Counter on this card at the end of the Damage Step. During your Main Phase: You can send this card to the Graveyard; Special Summon 1 monster from your hand whose Level is less than or equal to the number of Gate Counters on this card.",
    "str1": "Special Summon",
    "str2": "",
    "str3": "",
    "str4": "",
    "str5": "",
    "str6": "",
    "str7": "",
    "str8": "",
    "str9": "",
    "str10": "",
    "str11": "",
    "str12": "",
    "str13": "",
    "str14": "",
    "str15": "",
    "str16": "",
    "links": [],
    "cardpool": "OCG/TCG",
    "ocg": {
        "id": 97151365,
        "pack_id": "TDGS-JP067",
        "pack": "TDGS",
        "rarity": "Spacegate",
        "date": "2008-04-19"
    },
    "tcg": {
        "id": 97151365,
        "pack_id": "TDGS-EN067",
        "pack": "TDGS",
        "rarity": "Spacegate",
        "date": "2008-08-09"
    },
    "picture": "https://vignette.wikia.nocookie.net/yugioh/images/0/00/Spacegate-BP02-EN-C-1E.png/revision/latest?"
}