{
    "id": 97973962,
    "ot": 3,
    "alias": 0,
    "setcode": 0,
    "type": 67108897,
    "atk": 1800,
    "def": 5,
    "level": 2,
    "race": 2,
    "attribute": 32,
    "category": 528,
    "name": "Aleister the Invoker of Madness",
    "desc": "2 monsters with different Types and different Attributes\r\nThis card's name becomes \"Aleister the Invoker\" while on the field or in the GY. If a monster is Fusion Summoned while you control this monster (except during the Damage Step): You can discard 1 card, and if you do, add 1 \"Invocation\" or \"The Book of the Law\" from your Deck to your hand. If this face-up card you control leaves the field because of an opponent's card effect: You can add 1 \"Omega Summon\" from your Deck to your hand.",
    "str1": "Search \"Invocation\" or \"The Book of the Law\"",
    "str2": "Search \"Omega Summon\"",
    "str3": "",
    "str4": "",
    "str5": "",
    "str6": "",
    "str7": "",
    "str8": "",
    "str9": "",
    "str10": "",
    "str11": "",
    "str12": "",
    "str13": "",
    "str14": "",
    "str15": "",
    "str16": "",
    "cardpool": "OCG/TCG"
}