{
    "id": 98239899,
    "ot": 3,
    "alias": 0,
    "setcode": 0,
    "type": 4,
    "atk": 0,
    "def": 0,
    "level": 0,
    "race": 0,
    "attribute": 0,
    "category": 8195,
    "name": "Blast with Chain",
    "desc": "Target 1 face-up monster you control; equip this card to that target. It gains 500 ATK. If this card is destroyed by a card effect while equipped: Target 1 card on the field; destroy that target.",
    "str1": "",
    "str2": "",
    "str3": "",
    "str4": "",
    "str5": "",
    "str6": "",
    "str7": "",
    "str8": "",
    "str9": "",
    "str10": "",
    "str11": "",
    "str12": "",
    "str13": "",
    "str14": "",
    "str15": "",
    "str16": "",
    "links": [],
    "cardpool": "OCG/TCG",
    "ocg": {
        "id": 98239899,
        "pack_id": "MA-40",
        "pack": "Mythological Age",
        "rarity": "Blast with Chain",
        "date": "2001-11-29"
    },
    "tcg": {
        "id": 98239899,
        "pack_id": "LOD-088",
        "pack": "Legacy of Darkness",
        "rarity": "Blast with Chain",
        "date": "2003-06-06"
    },
    "picture": "https://vignette.wikia.nocookie.net/yugioh/images/3/30/BlastwithChain-BP03-EN-C-1E.png/revision/latest?cb=20140802103625"
}