{"id":99311109,"ot":3,"alias":0,"setcode":0,"type":4,"atk":0,"def":0,"level":0,"race":0,"attribute":0,"category":0,"name":"Oath of Companionship","desc":"If you control no monsters that were Special Summoned from the Extra Deck: Target 1 face-up monster your opponent controls that was Special Summoned from the Extra Deck; take control of it until the End Phase. You cannot Special Summon during the turn you activate this card.","str1":"","str2":"","str3":"","str4":"","str5":"","str6":"","str7":"","str8":"","str9":"","str10":"","str11":"","str12":"","str13":"","str14":"","str15":"","str16":"","links":[],"cardpool":"OCG/TCG","ocg":{"id":99311109,"pack_id":"LVAL-JP079","pack":"LVAL","rarity":"Oath of Companionship","date":1384560000000},"tcg":{"id":99311109,"pack_id":"LVAL-EN079","pack":"LVAL","rarity":"Oath of Companionship","date":1390521600000}}